odd_even_lang_packs/__init__.py
odd_even_lang_packs/main.py
test/__init__.py
test/test.py
odd_even_lang_packs-1.2.dist-info/LICENSE
odd_even_lang_packs-1.2.dist-info/METADATA
odd_even_lang_packs-1.2.dist-info/WHEEL
odd_even_lang_packs-1.2.dist-info/top_level.txt
odd_even_lang_packs-1.2.dist-info/RECORD
