Metadata-Version: 2.2
Name: odd_even_lang_packs
Version: 1.2
Summary: Language packs for the Odd Even application
Home-page: https://github.com/ergegananputra/odd_even_lang_packs
Author: Adiel Boanerge Gananputra
Author-email: ergegananputra@gmail.com
Classifier: Programming Language :: Python :: 3
Classifier: License :: OSI Approved :: MIT License
Classifier: Operating System :: OS Independent
Requires-Python: >=3.6
License-File: LICENSE
Dynamic: author
Dynamic: author-email
Dynamic: classifier
Dynamic: description
Dynamic: description-content-type
Dynamic: home-page
Dynamic: requires-python
Dynamic: summary
